<?xml version="1.0" encoding="UTF-8"?>
<beans xmlns="http://www.springframework.org/schema/beans"
	xmlns:xsi="http://www.w3.org/2001/XMLSchema-instance" xmlns:p="http://www.springframework.org/schema/p"
	xsi:schemaLocation="http://www.springframework.org/schema/beans
                    http://www.springframework.org/schema/beans/spring-beans-3.1.xsd">

	<bean id="LeaveApplicationView" parent="Uif-TransactionalDocumentView" p:headerText="Leave Application">
		<property name="documentClass" value="za.ac.nwu.bonsai.document.LeaveApplicationDocument" />
		<property name="formClass" value="za.ac.nwu.bonsai.form.LeaveApplicationForm" />
		<property name="items">
			<list>
				<ref bean="LeaveApplication-MainPage" />
			</list>
		</property>
	</bean>

	<bean id="LeaveApplication-MainPage" parent="Uif-DocumentPage">
		<property name="items">
			<list merge="true">
				<bean parent="Uif-GridGroup" p:fieldBindingObjectPath="leaveApplication" p:layoutManager.numberOfColumns="2">
					<property name="items">
						<list>
							<bean parent="Uif-InputField" p:propertyName="leaveType" p:label="Type"
								p:propertyEditorClass="za.ac.nwu.bonsai.propertyeditor.LeaveTypePropertyEditor">
								<property name="control">
									<bean parent="Uif-DropdownControl" />
								</property>
								<property name="optionsFinder">
									<bean class="za.ac.nwu.bonsai.keyvalue.LeaveTypeKeyValues" />
								</property>
							</bean>
							<bean parent="Uif-InputField" p:propertyName="dateFrom" p:label="From">
								<property name="control">
									<bean parent="Uif-DateControl" p:watermarkText="mm/dd/yyyy" />
								</property>
							</bean>
							<bean parent="Uif-InputField" p:propertyName="dateTo" p:label="To">
								<property name="control">
									<bean parent="Uif-DateControl" p:watermarkText="mm/dd/yyyy" />
								</property>
							</bean>
							<bean parent="Uif-InputField" p:propertyName="reason" p:label="Reason">
								<property name="control">
									<bean parent="Uif-TextAreaControl" p:rows="5" p:cols="50"
										p:textExpand="true" />
								</property>
							</bean>
							<bean parent="Uif-InputField" p:propertyName="contactNumber" p:label="Contact Number">
								<property name="control">
									<bean parent="Uif-TextControl" />
								</property>
							</bean>
							<bean parent="Uif-InputField" p:propertyName="contactAddress" p:label="Contact Adress">
								<property name="control">
									<bean parent="Uif-TextControl" />
								</property>
							</bean>
						</list>
					</property>
				</bean>
			</list>
		</property>
	</bean>

</beans>